aws_abort/__init__.py
aws_abort-0.0.1.dist-info/LICENSE
aws_abort-0.0.1.dist-info/METADATA
aws_abort-0.0.1.dist-info/WHEEL
aws_abort-0.0.1.dist-info/top_level.txt
aws_abort-0.0.1.dist-info/RECORD
