Metadata-Version: 2.2
Name: aws_abort
Version: 0.0.1
Summary: A lightweight Python package for handling HTTP error status codes by raising a custom exception with detailed, human-friendly messages.
Home-page: https://bitbucket.org/joetilsed/abort/src
Author: Joe Tilsed
Author-email: Joe@Tilsed.com
Classifier: Programming Language :: Python :: 3
Classifier: License :: OSI Approved :: MIT License
Classifier: Operating System :: OS Independent
License-File: LICENSE
Dynamic: author
Dynamic: author-email
Dynamic: classifier
Dynamic: description
Dynamic: description-content-type
Dynamic: home-page
Dynamic: summary
